ballchasing/__init__.py
ballchasing/api.py
ballchasing/constants.py
ballchasing/stats_info.tsv
ballchasing/util.py
ballchasing/typed/__init__.py
ballchasing/typed/deep_group.py
ballchasing/typed/deep_replay.py
ballchasing/typed/shallow_group.py
ballchasing/typed/shallow_replay.py
ballchasing/typed/shared.py
python_ballchasing-0.4.1.dist-info/licenses/LICENSE
scripts/make_types.py
scripts/test.py
scripts/test_typed.py
python_ballchasing-0.4.1.dist-info/METADATA
python_ballchasing-0.4.1.dist-info/WHEEL
python_ballchasing-0.4.1.dist-info/top_level.txt
python_ballchasing-0.4.1.dist-info/RECORD
