Metadata-Version: 2.4
Name: python-ballchasing
Version: 0.4.1
Summary: A Python wrapper around the Ballchasing API
Author-email: Rolv-Arild Braaten <rolv_arild@hotmail.com>
License: MIT License
Project-URL: Homepage, https://github.com/Rolv-Arild/python-ballchasing
Project-URL: Download, https://pypi.python.org/pypi/python-ballchasing
Classifier: Programming Language :: Python :: 3.9
Classifier: License :: OSI Approved :: MIT License
Classifier: Operating System :: OS Independent
Requires-Python: >=3.9
License-File: LICENSE
Requires-Dist: requests
Dynamic: license-file
